tantpy.py
tantpy-0.1.0.dist-info/METADATA
tantpy-0.1.0.dist-info/WHEEL
tantpy-0.1.0.dist-info/top_level.txt
tantpy-0.1.0.dist-info/RECORD
