Metadata-Version: 2.4
Name: tantpy
Version: 0.1.0
Summary: I should probably write a description here. Tant pis.
Requires-Python: >=3.12
